{
  "type": "flex",
  "altText": "Flex Message",
  "contents": {
    "type": "carousel",
    "contents": [
      {
        "type": "bubble",
        "direction": "ltr",
        "hero": {
          "type": "image",
          "url": "https://imgur.com/V1PJJwV.jpg",
          "size": "full",
          "aspectRatio": "20:13",
          "aspectMode": "cover"
        },
        "body": {
          "type": "box",
          "layout": "vertical",
          "spacing": "md",
          "contents": [
            {
              "type": "text",
              "text": "周而復始系列花茶",
              "size": "xl",
              "align": "center",
              "weight": "bold",
              "color": "#000000"
            },
            {
              "type": "text",
              "text": "共7種花茶飲，一週輕保養",
              "size": "xs",
              "align": "center",
              "weight": "regular",
              "color": "#AAAAAA",
              "wrap": true
            }
          ]
        },
        "footer": {
          "type": "box",
          "layout": "vertical",
          "spacing": "sm",
          "contents": [
            {
              "type": "button",
              "action": {
                "type": "message",
                "label": "進一步了解",
                "text": "進一步了解周而復始系列花茶"
              },
              "color": "#CFA37C",
              "height": "sm",
              "style": "primary"
            },
            {
              "type": "button",
              "action": {
                "type": "message",
                "label": "購買商品",
                "text": "購買周而復始系列花茶"
              },
              "color": "#AF4B69",
              "height": "sm",
              "style": "primary"
            }
          ]
        }
      },
      {
        "type": "bubble",
        "direction": "ltr",
        "hero": {
          "type": "image",
          "url": "https://i.imgur.com/9MKIq5o.jpg",
          "size": "full",
          "aspectRatio": "20:13",
          "aspectMode": "cover",
          "action": {
            "type": "uri",
            "label": "Action",
            "uri": "https://linecorp.com"
          }
        },
        "body": {
          "type": "box",
          "layout": "vertical",
          "spacing": "md",
          "action": {
            "type": "uri",
            "label": "Action",
            "uri": "https://linecorp.com"
          },
          "contents": [
            {
              "type": "text",
              "text": "小花集台灣特色花茶",
              "size": "xl",
              "align": "center",
              "weight": "bold"
            },
            {
              "type": "text",
              "text": "共6款優質在地茶飲",
              "size": "xs",
              "align": "center",
              "color": "#AAAAAA",
              "wrap": true
            }
          ]
        },
        "footer": {
          "type": "box",
          "layout": "vertical",
          "spacing": "sm",
          "contents": [
            {
              "type": "button",
              "action": {
                "type": "message",
                "label": "進一步了解",
                "text": "進一步了解台灣特色花茶"
              },
              "color": "#F0B0B0",
              "height": "sm",
              "style": "primary"
            },
            {
              "type": "button",
              "action": {
                "type": "message",
                "label": "查看完整系列商品",
                "text": "查看完整台灣特色花茶"
              },
              "color": "#C53C3C",
              "height": "sm",
              "style": "primary"
            }
          ]
        }
      },
      {
        "type": "bubble",
        "hero": {
          "type": "image",
          "url": "https://i.imgur.com/nTxRWr1.jpg",
          "size": "full",
          "aspectRatio": "20:13",
          "aspectMode": "cover",
          "action": {
            "type": "uri",
            "label": "Action",
            "uri": "https://linecorp.com"
          }
        },
        "body": {
          "type": "box",
          "layout": "vertical",
          "spacing": "md",
          "action": {
            "type": "uri",
            "label": "Action",
            "uri": "https://linecorp.com"
          },
          "contents": [
            {
              "type": "text",
              "text": "負能量系列花茶",
              "size": "xl",
              "align": "center",
              "weight": "bold"
            },
            {
              "type": "text",
              "text": "全系列共11款充滿負能量之產品",
              "size": "xs",
              "align": "center",
              "color": "#AAAAAA",
              "wrap": true
            }
          ]
        },
        "footer": {
          "type": "box",
          "layout": "vertical",
          "spacing": "sm",
          "contents": [
            {
              "type": "button",
              "action": {
                "type": "message",
                "label": "進一步了解",
                "text": "進一步了解負能量花茶"
              },
              "color": "#6A6866",
              "height": "sm",
              "style": "primary"
            },
            {
              "type": "button",
              "action": {
                "type": "message",
                "label": "查看完整系列商品",
                "text": "查看完整負能量系列花茶"
              },
              "color": "#141313",
              "height": "sm",
              "style": "primary"
            }
          ]
        }
      }
    ]
  }
}